aind_segmentation_evaluation/__init__.py
aind_segmentation_evaluation/conversions.py
aind_segmentation_evaluation/evaluate.py
aind_segmentation_evaluation/graph_routines.py
aind_segmentation_evaluation/merge_metric.py
aind_segmentation_evaluation/seg_metrics.py
aind_segmentation_evaluation/split_metric.py
aind_segmentation_evaluation/swc_routines.py
aind_segmentation_evaluation/utils.py
aind_segmentation_evaluation-0.1.48.dist-info/LICENSE
aind_segmentation_evaluation-0.1.48.dist-info/METADATA
aind_segmentation_evaluation-0.1.48.dist-info/WHEEL
aind_segmentation_evaluation-0.1.48.dist-info/top_level.txt
aind_segmentation_evaluation-0.1.48.dist-info/RECORD
